netspeedcli/__init__.py
netspeedcli/netspeed.py
netspeedcli/servers.py
netspeedcli/settings.json
akamai_speedtest-0.1.1.dist-info/LICENSE
akamai_speedtest-0.1.1.dist-info/METADATA
akamai_speedtest-0.1.1.dist-info/WHEEL
akamai_speedtest-0.1.1.dist-info/entry_points.txt
akamai_speedtest-0.1.1.dist-info/top_level.txt
akamai_speedtest-0.1.1.dist-info/RECORD
