Metadata-Version: 2.1
Name: akamai-speedtest
Version: 0.1.1
Summary: The Akamai servers based CLI tool for netspeed test
Author-email: YUcxovo <junglcuxo@sjtu.edu.cn>
License: MIT License
Keywords: speedtest,cli
Classifier: Programming Language :: Python :: 3
Requires-Python: >=3.7
License-File: LICENSE
Requires-Dist: typer
Requires-Dist: requests
Requires-Dist: psutil
Requires-Dist: ping3
Requires-Dist: typing-extensions
